alfenchargestation/__init__.py
alfenchargestation/alfenchargestation.py
alfencharger-5.42.dist-info/METADATA
alfencharger-5.42.dist-info/WHEEL
alfencharger-5.42.dist-info/licenses/LICENSE
alfencharger-5.42.dist-info/RECORD
