Metadata-Version: 2.3
Name: AlfenCharger
Version: 5.42
Summary: A Python library for controlling Alfen EV chargers
Project-URL: Homepage, https://github.com/HarmvandenBrink/Alfen_Chargestation_Reader_And_Controller
Project-URL: Issues, https://github.com/HarmvandenBrink/Alfen_Chargestation_Reader_And_Controller/issues
Author-email: Harm van den Brink <harmvandenbrink@gmail.com>
License-File: LICENSE
Classifier: License :: OSI Approved :: MIT License
Classifier: Operating System :: OS Independent
Classifier: Programming Language :: Python :: 3
Requires-Python: >=3.9
